pgpgram/__init__.py
pgpgram/color.py
pgpgram/config.py
pgpgram/libtdjson_Linux_x86_64.so
pgpgram/td.py
PGPgram-0.4.dist-info/LICENSE
PGPgram-0.4.dist-info/METADATA
PGPgram-0.4.dist-info/WHEEL
PGPgram-0.4.dist-info/entry_points.txt
PGPgram-0.4.dist-info/top_level.txt
PGPgram-0.4.dist-info/RECORD
