Metadata-Version: 2.1
Name: PGPgram
Version: 0.4
Summary: GPG encrypted backups on telegram
Home-page: https://github.com/tallero/PGPgram
Author: Pellegrino Prevete
Author-email: pellegrinoprevete@gmail.com
License: UNKNOWN
Platform: UNKNOWN
Classifier: Programming Language :: Python :: 3
Classifier: License :: OSI Approved :: GNU Affero General Public License v3 or later (AGPLv3+)
Classifier: Operating System :: Unix
Requires-Dist: appdirs
Requires-Dist: setproctitle
Requires-Dist: sqlitedict
Requires-Dist: trovotutto
